click_datetime/__init__.py
click_datetime-0.3.0.dist-info/METADATA
click_datetime-0.3.0.dist-info/WHEEL
click_datetime-0.3.0.dist-info/RECORD
