Metadata-Version: 2.1
Name: click-datetime
Version: 0.3.0
Summary: Datetime type support for click.
License: MIT
Author: Dawson R
Author-email: 105720-ddaws@users.noreply.gitlab.com
Requires-Python: >=3.12,<4.0
Classifier: License :: OSI Approved :: MIT License
Classifier: Programming Language :: Python :: 3
Classifier: Programming Language :: Python :: 3.12
Requires-Dist: click (>=6.6,<7.0)
Requires-Dist: wheel (>=0.44.0,<0.45.0)
